iex_api/__init__.py
iex_api/api/__init__.py
iex_api/api/api.py
iex_api/api/util.py
iex_api/api/model/__init__.py
iex_api/api/model/model.py
iex_api/model/__init__.py
iex_api/model/ca.py
iex_api/model/common.py
iex_api/model/company.py
iex_api/model/options.py
iex_api/model/stocks.py
iex_api-0.0.9.dist-info/LICENSE
iex_api-0.0.9.dist-info/METADATA
iex_api-0.0.9.dist-info/WHEEL
iex_api-0.0.9.dist-info/entry_points.txt
iex_api-0.0.9.dist-info/top_level.txt
iex_api-0.0.9.dist-info/RECORD
